{
  "TotalSessions": 2240,
  "TotalMessages": 2240,
  "TotalBlockedOperations": 0,
  "TotalPromptTokens": 3312,
  "TotalCompletionTokens": 2,
  "TotalDurationMs": 7616,
  "TopUsers": {
    "root": 866,
    "bot1": 20,
    "batman": 17,
    "oracle": 8,
    "felipe": 4,
    "administrator": 3,
    "mike": 2,
    "new": 2,
    "newuser1": 2,
    "roots": 2
  },
  "SessionsByBanner": {
    "SSH-2.0-dropbear_2020.80": 434,
    "SSH-2.0-OpenSSH_6.6.1": 425,
    "SSH-2.0-OpenSSH_7.2p2 Ubuntu": 660,
    "SSH-2.0-OpenSSH_for_Windows_8.1": 363,
    "SSH-2.0-OmegaBlack_Classified_Server_v1.0": 358
  },
  "MitreTechniqueDistribution": {
    "Execution": 2240,
    "Discovery": 2040,
    "Persistence": 587,
    "Command and Control": 576,
    "Reconnaissance": 2
  },
  "MeanEngagementSeconds": 0,
  "LastUpdated": "2026-07-17T13:46:30.7987671Z"
}