{
  "TotalSessions": 3661,
  "TotalMessages": 3660,
  "TotalBlockedOperations": 1,
  "TotalPromptTokens": 280054,
  "TotalCompletionTokens": 4789,
  "TotalDurationMs": 472794,
  "TopUsers": {
    "root": 1640,
    "admin": 269,
    "ftpuser": 16,
    "es": 4,
    "abe": 2,
    "arma3server": 2,
    "builder": 2,
    "calibre": 2,
    "simon": 2,
    "sinusbot": 2
  },
  "SessionsByBanner": {
    "SSH-2.0-OpenSSH_7.2p2 Ubuntu": 3661
  },
  "MitreTechniqueDistribution": {
    "Execution": 3660,
    "Discovery": 2404,
    "Persistence": 728,
    "Command and Control": 726,
    "Reconnaissance": 2
  },
  "MeanEngagementSeconds": 0.13,
  "LastUpdated": "2026-07-13T23:53:55.8460288Z"
}