{
  "TotalSessions": 2599,
  "TotalMessages": 2599,
  "TotalBlockedOperations": 0,
  "TotalPromptTokens": 7046243,
  "TotalCompletionTokens": 1350121,
  "TotalDurationMs": 60909237,
  "TopUsers": {
    "root": 1646,
    "postgres": 18,
    "test7": 10,
    "mrm": 4,
    "esadmin": 3,
    "accommodation": 2,
    "atlant": 2,
    "beer": 2,
    "cla": 2,
    "dennis": 2
  },
  "SessionsByBanner": {
    "SSH-2.0-OmegaBlack_Classified_Server_v1.0": 224,
    "SSH-2.0-dropbear_2020.80": 55,
    "SSH-2.0-OpenSSH_6.6.1": 2241,
    "SSH-2.0-OpenSSH_7.2p2 Ubuntu": 16,
    "SSH-2.0-OpenSSH_for_Windows_8.1": 63
  },
  "MitreTechniqueDistribution": {
    "Execution": 2599,
    "Persistence": 1132,
    "Command and Control": 1131,
    "Discovery": 2309,
    "Reconnaissance": 1
  },
  "MeanEngagementSeconds": 23.44,
  "LastUpdated": "2026-07-01T07:53:46.642317Z"
}