{
  "TotalSessions": 2956,
  "TotalMessages": 2956,
  "TotalBlockedOperations": 0,
  "TotalPromptTokens": 548358,
  "TotalCompletionTokens": 9213,
  "TotalDurationMs": 957570,
  "TopUsers": {
    "root": 799,
    "admin": 207,
    "ubuntu": 116,
    "administrator": 72,
    "postgres": 72,
    "acs": 2,
    "app": 2,
    "baptiste": 2,
    "c": 2,
    "didi": 2
  },
  "SessionsByBanner": {
    "SSH-2.0-OpenSSH_7.2p2 Ubuntu": 2956
  },
  "MitreTechniqueDistribution": {
    "Execution": 2956,
    "Discovery": 1371,
    "Persistence": 375,
    "Command and Control": 370,
    "Reconnaissance": 1
  },
  "MeanEngagementSeconds": 0.32,
  "LastUpdated": "2026-07-11T18:11:45.4330427Z"
}