{
  "TotalSessions": 162,
  "TotalMessages": 162,
  "TotalBlockedOperations": 0,
  "TotalPromptTokens": 0,
  "TotalCompletionTokens": 0,
  "TotalDurationMs": 2,
  "TopUsers": {
    "root": 58,
    "ubuntu": 7,
    "admin": 5,
    "administrator": 4,
    "app": 2,
    "baptiste": 2,
    "c": 2,
    "didi": 2,
    "postgres": 2,
    "andre": 1
  },
  "SessionsByBanner": {
    "SSH-2.0-OpenSSH_7.2p2 Ubuntu": 162
  },
  "MitreTechniqueDistribution": {
    "Execution": 162,
    "Discovery": 162,
    "Persistence": 42,
    "Command and Control": 42
  },
  "MeanEngagementSeconds": 0,
  "LastUpdated": "2026-07-10T14:58:29.0898136Z"
}