{
  "TotalSessions": 7246,
  "TotalMessages": 7243,
  "TotalBlockedOperations": 1,
  "TotalPromptTokens": 422941,
  "TotalCompletionTokens": 9959,
  "TotalDurationMs": 733360,
  "TopUsers": {
    "root": 3301,
    "admin": 436,
    "ftpuser": 36,
    "es": 8,
    "sinusbot": 4,
    "abe": 2,
    "arma3server": 2,
    "builder": 2,
    "calibre": 2,
    "simon": 2
  },
  "SessionsByBanner": {
    "SSH-2.0-OpenSSH_7.2p2 Ubuntu": 7246
  },
  "MitreTechniqueDistribution": {
    "Execution": 7243,
    "Discovery": 5033,
    "Persistence": 1428,
    "Command and Control": 1413,
    "Reconnaissance": 3
  },
  "MeanEngagementSeconds": 0.1,
  "LastUpdated": "2026-07-15T22:21:36.4978394Z"
}