{
  "TotalSessions": 1292,
  "TotalMessages": 1292,
  "TotalBlockedOperations": 0,
  "TotalPromptTokens": 144678,
  "TotalCompletionTokens": 1934,
  "TotalDurationMs": 202351,
  "TopUsers": {
    "root": 620,
    "admin": 80,
    "ftpuser": 6,
    "abe": 2,
    "arma3server": 2,
    "builder": 2,
    "calibre": 2,
    "es": 2,
    "simon": 2,
    "sinusbot": 2
  },
  "SessionsByBanner": {
    "SSH-2.0-OpenSSH_7.2p2 Ubuntu": 1292
  },
  "MitreTechniqueDistribution": {
    "Execution": 1292,
    "Discovery": 807,
    "Persistence": 241,
    "Command and Control": 238
  },
  "MeanEngagementSeconds": 0.16,
  "LastUpdated": "2026-07-12T19:22:19.4258376Z"
}