{
  "TotalSessions": 4075,
  "TotalMessages": 4075,
  "TotalBlockedOperations": 0,
  "TotalPromptTokens": 10826852,
  "TotalCompletionTokens": 2100979,
  "TotalDurationMs": 92741056,
  "TopUsers": {
    "root": 2671,
    "postgres": 28,
    "test7": 10,
    "dennis": 6,
    "mrm": 4,
    "esadmin": 3,
    "accommodation": 2,
    "atlant": 2,
    "beer": 2,
    "cla": 2
  },
  "SessionsByBanner": {
    "SSH-2.0-OmegaBlack_Classified_Server_v1.0": 224,
    "SSH-2.0-dropbear_2020.80": 55,
    "SSH-2.0-OpenSSH_6.6.1": 3717,
    "SSH-2.0-OpenSSH_7.2p2 Ubuntu": 16,
    "SSH-2.0-OpenSSH_for_Windows_8.1": 63
  },
  "MitreTechniqueDistribution": {
    "Execution": 4075,
    "Persistence": 1727,
    "Command and Control": 1725,
    "Discovery": 3530,
    "Reconnaissance": 1
  },
  "MeanEngagementSeconds": 22.76,
  "LastUpdated": "2026-07-02T14:36:54.0465919Z"
}