{
  "TotalSessions": 713,
  "TotalMessages": 714,
  "TotalBlockedOperations": 0,
  "TotalPromptTokens": 25015,
  "TotalCompletionTokens": 252,
  "TotalDurationMs": 43023,
  "TopUsers": {
    "root": 290,
    "admin": 21,
    "tunneluser": 4,
    "123": 3,
    "amine": 2,
    "arnaldo": 2,
    "erp": 2,
    "ftproot": 2,
    "gits": 2,
    "lucas": 2
  },
  "SessionsByBanner": {
    "SSH-2.0-OmegaBlack_Classified_Server_v1.0": 713
  },
  "MitreTechniqueDistribution": {
    "Execution": 714,
    "Discovery": 691,
    "Persistence": 195,
    "Command and Control": 195
  },
  "MeanEngagementSeconds": 0.06,
  "LastUpdated": "2026-07-20T20:29:49.6539748Z"
}