{
  "TotalSessions": 1491,
  "TotalMessages": 1492,
  "TotalBlockedOperations": 0,
  "TotalPromptTokens": 39769,
  "TotalCompletionTokens": 316,
  "TotalDurationMs": 91110,
  "TopUsers": {
    "root": 580,
    "admin": 36,
    "123": 4,
    "tunneluser": 4,
    "amine": 2,
    "arnaldo": 2,
    "erp": 2,
    "ftproot": 2,
    "gits": 2,
    "lucas": 2
  },
  "SessionsByBanner": {
    "SSH-2.0-OmegaBlack_Classified_Server_v1.0": 1491
  },
  "MitreTechniqueDistribution": {
    "Execution": 1492,
    "Discovery": 1452,
    "Persistence": 424,
    "Command and Control": 422
  },
  "MeanEngagementSeconds": 0.06,
  "LastUpdated": "2026-07-20T23:43:06.221409Z"
}