{
  "TotalSessions": 193,
  "TotalMessages": 191,
  "TotalBlockedOperations": 0,
  "TotalPromptTokens": 0,
  "TotalCompletionTokens": 0,
  "TotalDurationMs": 1,
  "TopUsers": {
    "root": 73,
    "mysql": 5,
    "crm": 4,
    "tianhao": 4,
    "admin": 3,
    "agro": 2,
    "deliver": 2,
    "postgres": 2,
    "user": 2,
    "yui": 2
  },
  "SessionsByBanner": {
    "SSH-2.0-OpenSSH_6.6.1": 71,
    "SSH-2.0-OpenSSH_7.2p2 Ubuntu": 95,
    "SSH-2.0-OpenSSH_for_Windows_8.1": 27
  },
  "MitreTechniqueDistribution": {
    "Execution": 177,
    "Persistence": 71,
    "Command and Control": 71,
    "Discovery": 172
  },
  "MeanEngagementSeconds": 0,
  "LastUpdated": "2026-06-13T22:57:29.265053Z"
}