{
  "TotalSessions": 6739,
  "TotalMessages": 6738,
  "TotalBlockedOperations": 1,
  "TotalPromptTokens": 416211,
  "TotalCompletionTokens": 9908,
  "TotalDurationMs": 726424,
  "TopUsers": {
    "root": 2961,
    "admin": 430,
    "ftpuser": 34,
    "es": 8,
    "sinusbot": 4,
    "abe": 2,
    "arma3server": 2,
    "builder": 2,
    "calibre": 2,
    "simon": 2
  },
  "SessionsByBanner": {
    "SSH-2.0-OpenSSH_7.2p2 Ubuntu": 6739
  },
  "MitreTechniqueDistribution": {
    "Execution": 6738,
    "Discovery": 4695,
    "Persistence": 1301,
    "Command and Control": 1285,
    "Reconnaissance": 3
  },
  "MeanEngagementSeconds": 0.11,
  "LastUpdated": "2026-07-15T15:57:01.4767262Z"
}