{
  "TotalSessions": 3622,
  "TotalMessages": 3622,
  "TotalBlockedOperations": 0,
  "TotalPromptTokens": 9731248,
  "TotalCompletionTokens": 1869719,
  "TotalDurationMs": 85015717,
  "TopUsers": {
    "root": 2443,
    "postgres": 22,
    "test7": 10,
    "dennis": 6,
    "mrm": 4,
    "esadmin": 3,
    "accommodation": 2,
    "atlant": 2,
    "beer": 2,
    "cla": 2
  },
  "SessionsByBanner": {
    "SSH-2.0-OmegaBlack_Classified_Server_v1.0": 224,
    "SSH-2.0-dropbear_2020.80": 55,
    "SSH-2.0-OpenSSH_6.6.1": 3264,
    "SSH-2.0-OpenSSH_7.2p2 Ubuntu": 16,
    "SSH-2.0-OpenSSH_for_Windows_8.1": 63
  },
  "MitreTechniqueDistribution": {
    "Execution": 3622,
    "Persistence": 1506,
    "Command and Control": 1504,
    "Discovery": 3080,
    "Reconnaissance": 1
  },
  "MeanEngagementSeconds": 23.47,
  "LastUpdated": "2026-07-02T03:27:51.0553446Z"
}