{
  "TotalSessions": 6791,
  "TotalMessages": 6790,
  "TotalBlockedOperations": 1,
  "TotalPromptTokens": 419576,
  "TotalCompletionTokens": 9938,
  "TotalDurationMs": 729599,
  "TopUsers": {
    "root": 2994,
    "admin": 430,
    "ftpuser": 34,
    "es": 8,
    "sinusbot": 4,
    "abe": 2,
    "arma3server": 2,
    "builder": 2,
    "calibre": 2,
    "simon": 2
  },
  "SessionsByBanner": {
    "SSH-2.0-OpenSSH_7.2p2 Ubuntu": 6791
  },
  "MitreTechniqueDistribution": {
    "Execution": 6790,
    "Discovery": 4739,
    "Persistence": 1314,
    "Command and Control": 1298,
    "Reconnaissance": 3
  },
  "MeanEngagementSeconds": 0.11,
  "LastUpdated": "2026-07-15T16:30:15.1540336Z"
}