{
  "TotalSessions": 8213,
  "TotalMessages": 8210,
  "TotalBlockedOperations": 1,
  "TotalPromptTokens": 463714,
  "TotalCompletionTokens": 11305,
  "TotalDurationMs": 805282,
  "TopUsers": {
    "root": 3593,
    "admin": 551,
    "ftpuser": 38,
    "es": 8,
    "builder": 6,
    "sinusbot": 4,
    "abe": 2,
    "arma3server": 2,
    "calibre": 2,
    "simon": 2
  },
  "SessionsByBanner": {
    "SSH-2.0-OpenSSH_7.2p2 Ubuntu": 8213
  },
  "MitreTechniqueDistribution": {
    "Execution": 8210,
    "Discovery": 5476,
    "Persistence": 1558,
    "Command and Control": 1540,
    "Reconnaissance": 3
  },
  "MeanEngagementSeconds": 0.1,
  "LastUpdated": "2026-07-16T05:11:34.3669023Z"
}