{
  "TotalSessions": 7305,
  "TotalMessages": 7302,
  "TotalBlockedOperations": 1,
  "TotalPromptTokens": 422941,
  "TotalCompletionTokens": 9959,
  "TotalDurationMs": 733360,
  "TopUsers": {
    "root": 3313,
    "admin": 436,
    "ftpuser": 36,
    "es": 8,
    "builder": 6,
    "sinusbot": 4,
    "abe": 2,
    "arma3server": 2,
    "calibre": 2,
    "simon": 2
  },
  "SessionsByBanner": {
    "SSH-2.0-OpenSSH_7.2p2 Ubuntu": 7305
  },
  "MitreTechniqueDistribution": {
    "Execution": 7302,
    "Discovery": 5092,
    "Persistence": 1453,
    "Command and Control": 1438,
    "Reconnaissance": 3
  },
  "MeanEngagementSeconds": 0.1,
  "LastUpdated": "2026-07-15T22:45:24.4324594Z"
}