{
  "TotalSessions": 2001,
  "TotalMessages": 2001,
  "TotalBlockedOperations": 0,
  "TotalPromptTokens": 5478395,
  "TotalCompletionTokens": 1061859,
  "TotalDurationMs": 48121452,
  "TopUsers": {
    "root": 1276,
    "postgres": 18,
    "test7": 10,
    "mrm": 4,
    "esadmin": 3,
    "accommodation": 2,
    "atlant": 2,
    "beer": 2,
    "cla": 2,
    "dennis": 2
  },
  "SessionsByBanner": {
    "SSH-2.0-OmegaBlack_Classified_Server_v1.0": 224,
    "SSH-2.0-dropbear_2020.80": 55,
    "SSH-2.0-OpenSSH_6.6.1": 1643,
    "SSH-2.0-OpenSSH_7.2p2 Ubuntu": 16,
    "SSH-2.0-OpenSSH_for_Windows_8.1": 63
  },
  "MitreTechniqueDistribution": {
    "Execution": 2001,
    "Persistence": 870,
    "Command and Control": 870,
    "Discovery": 1767
  },
  "MeanEngagementSeconds": 24.05,
  "LastUpdated": "2026-06-30T22:53:09.3851823Z"
}