{
  "TotalSessions": 3952,
  "TotalMessages": 3952,
  "TotalBlockedOperations": 0,
  "TotalPromptTokens": 10510438,
  "TotalCompletionTokens": 2047564,
  "TotalDurationMs": 90784251,
  "TopUsers": {
    "root": 2641,
    "postgres": 28,
    "test7": 10,
    "dennis": 6,
    "mrm": 4,
    "esadmin": 3,
    "accommodation": 2,
    "atlant": 2,
    "beer": 2,
    "cla": 2
  },
  "SessionsByBanner": {
    "SSH-2.0-OmegaBlack_Classified_Server_v1.0": 224,
    "SSH-2.0-dropbear_2020.80": 55,
    "SSH-2.0-OpenSSH_6.6.1": 3594,
    "SSH-2.0-OpenSSH_7.2p2 Ubuntu": 16,
    "SSH-2.0-OpenSSH_for_Windows_8.1": 63
  },
  "MitreTechniqueDistribution": {
    "Execution": 3952,
    "Persistence": 1667,
    "Command and Control": 1665,
    "Discovery": 3408,
    "Reconnaissance": 1
  },
  "MeanEngagementSeconds": 22.97,
  "LastUpdated": "2026-07-02T12:07:51.3322823Z"
}