{
  "TotalSessions": 3739,
  "TotalMessages": 3739,
  "TotalBlockedOperations": 0,
  "TotalPromptTokens": 10003032,
  "TotalCompletionTokens": 1928532,
  "TotalDurationMs": 87105134,
  "TopUsers": {
    "root": 2530,
    "postgres": 26,
    "test7": 10,
    "dennis": 6,
    "mrm": 4,
    "esadmin": 3,
    "accommodation": 2,
    "atlant": 2,
    "beer": 2,
    "cla": 2
  },
  "SessionsByBanner": {
    "SSH-2.0-OmegaBlack_Classified_Server_v1.0": 224,
    "SSH-2.0-dropbear_2020.80": 55,
    "SSH-2.0-OpenSSH_6.6.1": 3381,
    "SSH-2.0-OpenSSH_7.2p2 Ubuntu": 16,
    "SSH-2.0-OpenSSH_for_Windows_8.1": 63
  },
  "MitreTechniqueDistribution": {
    "Execution": 3739,
    "Persistence": 1563,
    "Command and Control": 1561,
    "Discovery": 3197,
    "Reconnaissance": 1
  },
  "MeanEngagementSeconds": 23.3,
  "LastUpdated": "2026-07-02T05:58:09.3413203Z"
}