{
  "TotalSessions": 3195,
  "TotalMessages": 3195,
  "TotalBlockedOperations": 0,
  "TotalPromptTokens": 8717819,
  "TotalCompletionTokens": 1649660,
  "TotalDurationMs": 77014298,
  "TopUsers": {
    "root": 2119,
    "postgres": 20,
    "test7": 10,
    "mrm": 4,
    "esadmin": 3,
    "accommodation": 2,
    "atlant": 2,
    "beer": 2,
    "cla": 2,
    "dennis": 2
  },
  "SessionsByBanner": {
    "SSH-2.0-OmegaBlack_Classified_Server_v1.0": 224,
    "SSH-2.0-dropbear_2020.80": 55,
    "SSH-2.0-OpenSSH_6.6.1": 2837,
    "SSH-2.0-OpenSSH_7.2p2 Ubuntu": 16,
    "SSH-2.0-OpenSSH_for_Windows_8.1": 63
  },
  "MitreTechniqueDistribution": {
    "Execution": 3195,
    "Persistence": 1350,
    "Command and Control": 1349,
    "Discovery": 2760,
    "Reconnaissance": 1
  },
  "MeanEngagementSeconds": 24.1,
  "LastUpdated": "2026-07-01T19:47:30.4366036Z"
}