{
  "TotalSessions": 6,
  "TotalMessages": 6,
  "TotalBlockedOperations": 0,
  "TotalPromptTokens": 14196,
  "TotalCompletionTokens": 4171,
  "TotalDurationMs": 97413,
  "TopUsers": {
    "db2fenc": 1,
    "ali": 2,
    "newuser": 1,
    "root": 2
  },
  "SessionsByBanner": {
    "SSH-2.0-OmegaBlack_Classified_Server_v1.0": 6
  },
  "MitreTechniqueDistribution": {
    "Execution": 6,
    "Discovery": 6,
    "Persistence": 2,
    "Command and Control": 2
  },
  "MeanEngagementSeconds": 16.24,
  "LastUpdated": "2026-06-29T19:23:47.7890593Z"
}