{
  "TotalSessions": 10,
  "TotalMessages": 10,
  "TotalBlockedOperations": 0,
  "TotalPromptTokens": 18325,
  "TotalCompletionTokens": 20,
  "TotalDurationMs": 34151,
  "TopUsers": {
    "pop": 1,
    "admin": 2,
    "test1": 1,
    "odoo": 1,
    "root": 4,
    "bert": 1
  },
  "SessionsByBanner": {
    "SSH-2.0-OmegaBlack_Classified_Server_v1.0": 10
  },
  "MitreTechniqueDistribution": {
    "Execution": 10,
    "Persistence": 5,
    "Command and Control": 5,
    "Discovery": 10
  },
  "MeanEngagementSeconds": 3.42,
  "LastUpdated": "2026-07-09T05:30:15.0778334Z"
}