{
  "TotalSessions": 4651,
  "TotalMessages": 4651,
  "TotalBlockedOperations": 0,
  "TotalPromptTokens": 12084814,
  "TotalCompletionTokens": 2350864,
  "TotalDurationMs": 102044530,
  "TopUsers": {
    "root": 3088,
    "postgres": 37,
    "test7": 10,
    "dennis": 6,
    "mrm": 4,
    "esadmin": 3,
    "accommodation": 2,
    "atlant": 2,
    "beer": 2,
    "cla": 2
  },
  "SessionsByBanner": {
    "SSH-2.0-OmegaBlack_Classified_Server_v1.0": 224,
    "SSH-2.0-dropbear_2020.80": 55,
    "SSH-2.0-OpenSSH_6.6.1": 4293,
    "SSH-2.0-OpenSSH_7.2p2 Ubuntu": 16,
    "SSH-2.0-OpenSSH_for_Windows_8.1": 63
  },
  "MitreTechniqueDistribution": {
    "Execution": 4651,
    "Persistence": 1997,
    "Command and Control": 1995,
    "Discovery": 4081,
    "Reconnaissance": 1
  },
  "MeanEngagementSeconds": 21.94,
  "LastUpdated": "2026-07-03T01:15:28.5858338Z"
}