{
  "TotalSessions": 2560,
  "TotalMessages": 2560,
  "TotalBlockedOperations": 0,
  "TotalPromptTokens": 6772,
  "TotalCompletionTokens": 617,
  "TotalDurationMs": 18205,
  "TopUsers": {
    "root": 1034,
    "bot1": 20,
    "batman": 17,
    "oracle": 11,
    "felipe": 4,
    "administrator": 3,
    "mike": 2,
    "new": 2,
    "newuser1": 2,
    "roots": 2
  },
  "SessionsByBanner": {
    "SSH-2.0-dropbear_2020.80": 465,
    "SSH-2.0-OpenSSH_6.6.1": 467,
    "SSH-2.0-OpenSSH_7.2p2 Ubuntu": 780,
    "SSH-2.0-OpenSSH_for_Windows_8.1": 415,
    "SSH-2.0-OmegaBlack_Classified_Server_v1.0": 433
  },
  "MitreTechniqueDistribution": {
    "Execution": 2560,
    "Discovery": 2321,
    "Persistence": 675,
    "Command and Control": 663,
    "Reconnaissance": 2
  },
  "MeanEngagementSeconds": 0.01,
  "LastUpdated": "2026-07-17T19:50:31.2007613Z"
}