{
  "TotalSessions": 485,
  "TotalMessages": 485,
  "TotalBlockedOperations": 0,
  "TotalPromptTokens": 127868,
  "TotalCompletionTokens": 187,
  "TotalDurationMs": 148764,
  "TopUsers": {
    "root": 258,
    "admin": 51,
    "ftpuser": 4,
    "abe": 2,
    "arma3server": 2,
    "builder": 2,
    "calibre": 2,
    "es": 2,
    "simon": 2,
    "sinusbot": 2
  },
  "SessionsByBanner": {
    "SSH-2.0-OpenSSH_7.2p2 Ubuntu": 485
  },
  "MitreTechniqueDistribution": {
    "Execution": 485,
    "Discovery": 245,
    "Persistence": 81,
    "Command and Control": 80
  },
  "MeanEngagementSeconds": 0.31,
  "LastUpdated": "2026-07-12T13:14:10.332361Z"
}