{
  "TotalSessions": 24,
  "TotalMessages": 24,
  "TotalBlockedOperations": 0,
  "TotalPromptTokens": 6356,
  "TotalCompletionTokens": 379,
  "TotalDurationMs": 77723,
  "TopUsers": {
    "root": 11,
    "sol": 11,
    "ubuntu": 2
  },
  "SessionsByInfrastructureCategory": {
    "unknown": 24
  },
  "SessionsByBanner": {
    "SSH-2.0-OpenSSH_for_Windows_8.1": 6,
    "SSH-2.0-OmegaBlack_Classified_Server_v1.0": 9,
    "SSH-2.0-OpenSSH_6.6.1": 9
  },
  "MitreTechniqueDistribution": {},
  "MeanEngagementSeconds": 3.24,
  "LastUpdated": "2026-05-23T22:50:40.708343Z"
}