{
  "TotalSessions": 564,
  "TotalMessages": 564,
  "TotalBlockedOperations": 0,
  "TotalPromptTokens": 127868,
  "TotalCompletionTokens": 187,
  "TotalDurationMs": 148764,
  "TopUsers": {
    "root": 291,
    "admin": 54,
    "ftpuser": 4,
    "abe": 2,
    "arma3server": 2,
    "builder": 2,
    "calibre": 2,
    "es": 2,
    "simon": 2,
    "sinusbot": 2
  },
  "SessionsByBanner": {
    "SSH-2.0-OpenSSH_7.2p2 Ubuntu": 564
  },
  "MitreTechniqueDistribution": {
    "Execution": 564,
    "Discovery": 323,
    "Persistence": 105,
    "Command and Control": 104
  },
  "MeanEngagementSeconds": 0.26,
  "LastUpdated": "2026-07-12T14:05:13.0312121Z"
}