{
  "TotalSessions": 973,
  "TotalMessages": 973,
  "TotalBlockedOperations": 0,
  "TotalPromptTokens": 0,
  "TotalCompletionTokens": 0,
  "TotalDurationMs": 5954,
  "TopUsers": {
    "root": 348,
    "bot1": 20,
    "batman": 17,
    "oracle": 4,
    "felipe": 3,
    "administrator": 2,
    "mike": 2,
    "new": 2,
    "newuser1": 2,
    "roots": 2
  },
  "SessionsByBanner": {
    "SSH-2.0-dropbear_2020.80": 138,
    "SSH-2.0-OpenSSH_6.6.1": 239,
    "SSH-2.0-OpenSSH_7.2p2 Ubuntu": 230,
    "SSH-2.0-OpenSSH_for_Windows_8.1": 158,
    "SSH-2.0-OmegaBlack_Classified_Server_v1.0": 208
  },
  "MitreTechniqueDistribution": {
    "Execution": 973,
    "Discovery": 884,
    "Persistence": 276,
    "Command and Control": 269,
    "Reconnaissance": 1
  },
  "MeanEngagementSeconds": 0.01,
  "LastUpdated": "2026-07-16T18:16:11.6562233Z"
}