{
  "TotalSessions": 333,
  "TotalMessages": 333,
  "TotalBlockedOperations": 0,
  "TotalPromptTokens": 121366,
  "TotalCompletionTokens": 4038,
  "TotalDurationMs": 150046,
  "TopUsers": {
    "root": 186,
    "admin": 7,
    "ubuntu": 7,
    "administrator": 4,
    "app": 2,
    "baptiste": 2,
    "c": 2,
    "didi": 2,
    "postgres": 2,
    "admin123": 1
  },
  "SessionsByBanner": {
    "SSH-2.0-OpenSSH_7.2p2 Ubuntu": 333
  },
  "MitreTechniqueDistribution": {
    "Execution": 333,
    "Discovery": 241,
    "Persistence": 58,
    "Command and Control": 58
  },
  "MeanEngagementSeconds": 0.45,
  "LastUpdated": "2026-07-10T18:57:16.7902745Z"
}