{
  "TotalSessions": 7844,
  "TotalMessages": 7841,
  "TotalBlockedOperations": 1,
  "TotalPromptTokens": 440028,
  "TotalCompletionTokens": 10052,
  "TotalDurationMs": 747096,
  "TopUsers": {
    "root": 3475,
    "admin": 500,
    "ftpuser": 38,
    "es": 8,
    "builder": 6,
    "sinusbot": 4,
    "abe": 2,
    "arma3server": 2,
    "calibre": 2,
    "simon": 2
  },
  "SessionsByBanner": {
    "SSH-2.0-OpenSSH_7.2p2 Ubuntu": 7844
  },
  "MitreTechniqueDistribution": {
    "Execution": 7841,
    "Discovery": 5364,
    "Persistence": 1540,
    "Command and Control": 1524,
    "Reconnaissance": 3
  },
  "MeanEngagementSeconds": 0.1,
  "LastUpdated": "2026-07-16T02:19:05.8675919Z"
}