{
  "TotalSessions": 1330,
  "TotalMessages": 1340,
  "TotalBlockedOperations": 0,
  "TotalPromptTokens": 101335,
  "TotalCompletionTokens": 2930,
  "TotalDurationMs": 150483,
  "TopUsers": {
    "root": 525,
    "admin": 29,
    "deploy": 13,
    "git": 10,
    "postgres": 6,
    "aa": 3,
    "abhishek": 2,
    "asep": 2,
    "a": 1,
    "a1": 1
  },
  "SessionsByBanner": {
    "SSH-2.0-OpenSSH_7.2p2 Ubuntu": 117,
    "SSH-2.0-OpenSSH_for_Windows_8.1": 220,
    "SSH-2.0-OmegaBlack_Classified_Server_v1.0": 86,
    "SSH-2.0-dropbear_2020.80": 823,
    "SSH-2.0-OpenSSH_6.6.1": 84
  },
  "MitreTechniqueDistribution": {
    "Execution": 1340,
    "Persistence": 294,
    "Command and Control": 295,
    "Discovery": 1250
  },
  "MeanEngagementSeconds": 0.11,
  "LastUpdated": "2026-07-10T10:29:35.2534889Z"
}