{
  "TotalSessions": 49,
  "TotalMessages": 49,
  "TotalBlockedOperations": 0,
  "TotalPromptTokens": 140214,
  "TotalCompletionTokens": 25354,
  "TotalDurationMs": 877162,
  "TopUsers": {
    "root": 43,
    "postgres": 3,
    "ubuntu": 1,
    "dennis": 2
  },
  "SessionsByBanner": {
    "SSH-2.0-OmegaBlack_Classified_Server_v1.0": 49
  },
  "MitreTechniqueDistribution": {
    "Execution": 49,
    "Persistence": 27,
    "Command and Control": 27,
    "Discovery": 48
  },
  "MeanEngagementSeconds": 17.9,
  "LastUpdated": "2026-06-29T23:27:38.2479618Z"
}