{
  "TotalSessions": 2104,
  "TotalMessages": 2104,
  "TotalBlockedOperations": 0,
  "TotalPromptTokens": 3312,
  "TotalCompletionTokens": 2,
  "TotalDurationMs": 7614,
  "TopUsers": {
    "root": 800,
    "bot1": 20,
    "batman": 17,
    "oracle": 8,
    "felipe": 4,
    "administrator": 3,
    "mike": 2,
    "new": 2,
    "newuser1": 2,
    "roots": 2
  },
  "SessionsByBanner": {
    "SSH-2.0-dropbear_2020.80": 393,
    "SSH-2.0-OpenSSH_6.6.1": 413,
    "SSH-2.0-OpenSSH_7.2p2 Ubuntu": 644,
    "SSH-2.0-OpenSSH_for_Windows_8.1": 316,
    "SSH-2.0-OmegaBlack_Classified_Server_v1.0": 338
  },
  "MitreTechniqueDistribution": {
    "Execution": 2104,
    "Discovery": 1924,
    "Persistence": 553,
    "Command and Control": 543,
    "Reconnaissance": 2
  },
  "MeanEngagementSeconds": 0,
  "LastUpdated": "2026-07-17T11:57:29.4057594Z"
}