{
  "TotalSessions": 1095,
  "TotalMessages": 1095,
  "TotalBlockedOperations": 0,
  "TotalPromptTokens": 141311,
  "TotalCompletionTokens": 1845,
  "TotalDurationMs": 198120,
  "TopUsers": {
    "root": 556,
    "admin": 77,
    "ftpuser": 5,
    "abe": 2,
    "arma3server": 2,
    "builder": 2,
    "calibre": 2,
    "es": 2,
    "simon": 2,
    "sinusbot": 2
  },
  "SessionsByBanner": {
    "SSH-2.0-OpenSSH_7.2p2 Ubuntu": 1095
  },
  "MitreTechniqueDistribution": {
    "Execution": 1095,
    "Discovery": 629,
    "Persistence": 193,
    "Command and Control": 191
  },
  "MeanEngagementSeconds": 0.18,
  "LastUpdated": "2026-07-12T18:38:42.879105Z"
}