{
  "TotalSessions": 1516,
  "TotalMessages": 1517,
  "TotalBlockedOperations": 0,
  "TotalPromptTokens": 39769,
  "TotalCompletionTokens": 316,
  "TotalDurationMs": 91110,
  "TopUsers": {
    "root": 590,
    "admin": 36,
    "123": 4,
    "tunneluser": 4,
    "amine": 2,
    "arnaldo": 2,
    "erp": 2,
    "ftproot": 2,
    "gits": 2,
    "lucas": 2
  },
  "SessionsByBanner": {
    "SSH-2.0-OmegaBlack_Classified_Server_v1.0": 1516
  },
  "MitreTechniqueDistribution": {
    "Execution": 1517,
    "Discovery": 1476,
    "Persistence": 432,
    "Command and Control": 430
  },
  "MeanEngagementSeconds": 0.06,
  "LastUpdated": "2026-07-20T23:53:40.410815Z"
}