{
  "TotalSessions": 4885,
  "TotalMessages": 4884,
  "TotalBlockedOperations": 1,
  "TotalPromptTokens": 296889,
  "TotalCompletionTokens": 4955,
  "TotalDurationMs": 494951,
  "TopUsers": {
    "root": 2090,
    "admin": 289,
    "ftpuser": 30,
    "es": 5,
    "sinusbot": 4,
    "abe": 2,
    "arma3server": 2,
    "builder": 2,
    "calibre": 2,
    "simon": 2
  },
  "SessionsByBanner": {
    "SSH-2.0-OpenSSH_7.2p2 Ubuntu": 4885
  },
  "MitreTechniqueDistribution": {
    "Execution": 4884,
    "Discovery": 3525,
    "Persistence": 996,
    "Command and Control": 991,
    "Reconnaissance": 2
  },
  "MeanEngagementSeconds": 0.1,
  "LastUpdated": "2026-07-14T15:25:21.7474534Z"
}