{
  "TotalSessions": 4167,
  "TotalMessages": 4166,
  "TotalBlockedOperations": 1,
  "TotalPromptTokens": 286803,
  "TotalCompletionTokens": 4856,
  "TotalDurationMs": 480730,
  "TopUsers": {
    "root": 1809,
    "admin": 281,
    "ftpuser": 19,
    "es": 4,
    "sinusbot": 4,
    "abe": 2,
    "arma3server": 2,
    "builder": 2,
    "calibre": 2,
    "simon": 2
  },
  "SessionsByBanner": {
    "SSH-2.0-OpenSSH_7.2p2 Ubuntu": 4167
  },
  "MitreTechniqueDistribution": {
    "Execution": 4166,
    "Discovery": 2847,
    "Persistence": 831,
    "Command and Control": 828,
    "Reconnaissance": 2
  },
  "MeanEngagementSeconds": 0.12,
  "LastUpdated": "2026-07-14T08:56:16.9894993Z"
}