{
  "TotalSessions": 89,
  "TotalMessages": 89,
  "TotalBlockedOperations": 0,
  "TotalPromptTokens": 0,
  "TotalCompletionTokens": 0,
  "TotalDurationMs": 1,
  "TopUsers": {
    "root": 41,
    "mysql": 4,
    "admin": 2,
    "agro": 2,
    "crm": 2,
    "deliver": 2,
    "postgres": 2,
    "tianhao": 2,
    "user": 2,
    "yui": 2
  },
  "SessionsByBanner": {
    "SSH-2.0-OpenSSH_6.6.1": 71,
    "SSH-2.0-OpenSSH_7.2p2 Ubuntu": 18
  },
  "MitreTechniqueDistribution": {
    "Execution": 85,
    "Persistence": 37,
    "Command and Control": 37,
    "Discovery": 83
  },
  "MeanEngagementSeconds": 0,
  "LastUpdated": "2026-06-13T22:28:42.2251446Z"
}