{
  "TotalSessions": 19,
  "TotalMessages": 19,
  "TotalBlockedOperations": 0,
  "TotalPromptTokens": 40327,
  "TotalCompletionTokens": 44,
  "TotalDurationMs": 64597,
  "TopUsers": {
    "root": 5,
    "admin": 2,
    "bert": 2,
    "jack": 2,
    "azureuser": 1,
    "cs2server": 1,
    "guilherme": 1,
    "leandro": 1,
    "odoo": 1,
    "pop": 1
  },
  "SessionsByBanner": {
    "SSH-2.0-OmegaBlack_Classified_Server_v1.0": 19
  },
  "MitreTechniqueDistribution": {
    "Execution": 19,
    "Persistence": 11,
    "Command and Control": 11,
    "Discovery": 19
  },
  "MeanEngagementSeconds": 3.4,
  "LastUpdated": "2026-07-09T05:33:44.7681955Z"
}