{
  "TotalSessions": 153,
  "TotalMessages": 150,
  "TotalBlockedOperations": 0,
  "TotalPromptTokens": 0,
  "TotalCompletionTokens": 0,
  "TotalDurationMs": 1,
  "TopUsers": {
    "root": 24,
    "admin": 6,
    "dino": 4,
    "ubuntu": 4,
    "demo": 2,
    "junin": 2,
    "sql": 2,
    "tom": 2,
    "viking": 2,
    "windows2": 2
  },
  "SessionsByBanner": {
    "SSH-2.0-OpenSSH_7.2p2 Ubuntu": 145,
    "SSH-2.0-OpenSSH_for_Windows_8.1": 8
  },
  "MitreTechniqueDistribution": {
    "Execution": 139,
    "Discovery": 137,
    "Persistence": 56,
    "Command and Control": 56
  },
  "MeanEngagementSeconds": 0,
  "LastUpdated": "2026-06-24T15:55:49.2163995Z"
}