{
  "TotalSessions": 3846,
  "TotalMessages": 3846,
  "TotalBlockedOperations": 0,
  "TotalPromptTokens": 561765,
  "TotalCompletionTokens": 9326,
  "TotalDurationMs": 966254,
  "TopUsers": {
    "root": 1138,
    "admin": 218,
    "ubuntu": 137,
    "postgres": 79,
    "administrator": 72,
    "c": 3,
    "acs": 2,
    "app": 2,
    "baptiste": 2,
    "didi": 2
  },
  "SessionsByBanner": {
    "SSH-2.0-OpenSSH_7.2p2 Ubuntu": 3846
  },
  "MitreTechniqueDistribution": {
    "Execution": 3846,
    "Discovery": 2235,
    "Persistence": 639,
    "Command and Control": 631,
    "Reconnaissance": 1
  },
  "MeanEngagementSeconds": 0.25,
  "LastUpdated": "2026-07-12T03:44:18.3776418Z"
}