{
  "TotalSessions": 2121,
  "TotalMessages": 2121,
  "TotalBlockedOperations": 0,
  "TotalPromptTokens": 418600,
  "TotalCompletionTokens": 7182,
  "TotalDurationMs": 716256,
  "TopUsers": {
    "root": 498,
    "admin": 191,
    "ubuntu": 99,
    "administrator": 70,
    "postgres": 65,
    "acs": 2,
    "app": 2,
    "baptiste": 2,
    "c": 2,
    "didi": 2
  },
  "SessionsByBanner": {
    "SSH-2.0-OpenSSH_7.2p2 Ubuntu": 2121
  },
  "MitreTechniqueDistribution": {
    "Execution": 2121,
    "Discovery": 764,
    "Persistence": 222,
    "Command and Control": 217
  },
  "MeanEngagementSeconds": 0.34,
  "LastUpdated": "2026-07-11T05:24:25.9271809Z"
}