{
  "TotalSessions": 6252,
  "TotalMessages": 6251,
  "TotalBlockedOperations": 1,
  "TotalPromptTokens": 381892,
  "TotalCompletionTokens": 9738,
  "TotalDurationMs": 695250,
  "TopUsers": {
    "root": 2693,
    "admin": 392,
    "ftpuser": 32,
    "es": 8,
    "sinusbot": 4,
    "abe": 2,
    "arma3server": 2,
    "builder": 2,
    "calibre": 2,
    "simon": 2
  },
  "SessionsByBanner": {
    "SSH-2.0-OpenSSH_7.2p2 Ubuntu": 6252
  },
  "MitreTechniqueDistribution": {
    "Execution": 6251,
    "Discovery": 4419,
    "Persistence": 1222,
    "Command and Control": 1211,
    "Reconnaissance": 3
  },
  "MeanEngagementSeconds": 0.11,
  "LastUpdated": "2026-07-15T12:45:24.9154561Z"
}