{
  "LastUpdated": "2026-07-12T10:36:41.9402329Z",
  "TotalEvents": 99,
  "TotalScanAttempts": 12,
  "UniqueScanIps": 1,
  "TotalShells": 18,
  "EventCounts": {
    "session_end": 8,
    "session_start": 7,
    "auth_attempt": 6,
    "harvested_credential": 6,
    "shell_session_start": 18,
    "command": 18,
    "command_result": 18,
    "shell_session_end": 18
  },
  "ScansByIp": {
    "92.118.39.71": 12
  },
  "TopUsernames": {
    "root": 12
  },
  "TopPasswords": {
    "root5678": 2,
    "root6666": 2,
    "root9999": 2,
    "root@123": 2,
    "rootaccess": 2,
    "rootadmin": 2
  }
}