{
  "LastUpdated": "2026-07-16T16:29:04.4367325Z",
  "TotalEvents": 204,
  "TotalScanAttempts": 64,
  "UniqueScanIps": 6,
  "TotalShells": 18,
  "EventCounts": {
    "auth_attempt": 32,
    "harvested_credential": 32,
    "shell_session_start": 18,
    "session_start": 39,
    "command": 18,
    "command_result": 18,
    "shell_session_end": 18,
    "session_end": 29
  },
  "ScansByIp": {
    "103.208.219.38": 16,
    "141.11.0.200": 10,
    "103.67.80.61": 12,
    "194.31.223.71": 18,
    "171.244.201.80": 6,
    "89.163.204.62": 2
  },
  "TopUsernames": {
    "345gs5662d34": 18,
    "mailuser": 2,
    "mini": 4,
    "cody": 4,
    "root": 16,
    "mathias": 4,
    "wireguard": 4,
    "icp": 4,
    "admin": 2,
    "shashank": 4,
    "systemd": 2
  },
  "TopPasswords": {
    "345gs5662d34": 18,
    "3245gs5662d34": 22,
    "mini": 2,
    "cody": 2,
    "Ws123456@": 2,
    "mathias": 2,
    "root": 2,
    "12345": 2,
    "qwer@1234": 2,
    "Qweasd2025": 2,
    "admin12345": 2,
    "shashank@123": 2,
    "systemd": 2,
    "Admin12!": 2
  }
}