{
  "LastUpdated": "2026-07-19T05:24:28.686966Z",
  "TotalEvents": 138,
  "TotalScanAttempts": 28,
  "UniqueScanIps": 4,
  "TotalShells": 19,
  "EventCounts": {
    "session_start": 23,
    "auth_attempt": 14,
    "harvested_credential": 14,
    "shell_session_start": 19,
    "command": 19,
    "command_result": 18,
    "shell_session_end": 18,
    "session_end": 13
  },
  "ScansByIp": {
    "172.252.13.101": 2,
    "182.76.43.24": 2,
    "14.29.240.154": 18,
    "103.154.77.48": 6
  },
  "TopUsernames": {
    "root": 14,
    "345gs5662d34": 8,
    "amit": 4,
    "rita": 2
  },
  "TopPasswords": {
    "spartak": 2,
    "qwe123rty456": 2,
    "345gs5662d34": 8,
    "3245gs5662d34": 8,
    "amit": 2,
    "123698745": 2,
    "Password\u002B1": 2,
    "rita@123": 2
  }
}