{
  "LastUpdated": "2026-07-10T11:42:51.3512587Z",
  "TotalEvents": 49,
  "TotalScanAttempts": 16,
  "UniqueScanIps": 3,
  "TotalShells": 5,
  "EventCounts": {
    "session_start": 8,
    "auth_attempt": 8,
    "harvested_credential": 8,
    "shell_session_start": 5,
    "command": 5,
    "command_result": 5,
    "shell_session_end": 5,
    "session_end": 5
  },
  "ScansByIp": {
    "122.35.192.33": 6,
    "61.155.106.101": 6,
    "24.122.136.94": 4
  },
  "TopUsernames": {
    "firewall2": 4,
    "345gs5662d34": 6,
    "jenkins": 4,
    "root": 2
  },
  "TopPasswords": {
    "firewall2": 2,
    "345gs5662d34": 6,
    "3245gs5662d34": 4,
    "q1w2e3r4": 2,
    "QAZwsx12": 2
  }
}