{
  "LastUpdated": "2026-07-12T14:46:57.2997221Z",
  "TotalEvents": 48,
  "TotalScanAttempts": 10,
  "UniqueScanIps": 3,
  "TotalShells": 6,
  "EventCounts": {
    "shell_session_start": 6,
    "session_start": 8,
    "command": 6,
    "command_result": 6,
    "shell_session_end": 6,
    "session_end": 6,
    "auth_attempt": 5,
    "harvested_credential": 5
  },
  "ScansByIp": {
    "101.47.156.21": 2,
    "195.178.110.227": 2,
    "182.93.7.194": 6
  },
  "TopUsernames": {
    "cvs": 2,
    "root": 6,
    "345gs5662d34": 2
  },
  "TopPasswords": {
    "3245gs5662d34": 4,
    "123456": 2,
    "Password1#": 2,
    "345gs5662d34": 2
  }
}