{
  "LastUpdated": "2026-06-29T15:09:39.9353777Z",
  "TotalEvents": 169,
  "TotalScanAttempts": 50,
  "UniqueScanIps": 1,
  "TotalShells": 16,
  "EventCounts": {
    "session_start": 28,
    "session_end": 27,
    "auth_attempt": 25,
    "harvested_credential": 25,
    "shell_session_start": 16,
    "command": 16,
    "shell_session_end": 16,
    "command_result": 16
  },
  "ScansByIp": {
    "103.163.117.83": 50
  },
  "TopUsernames": {
    "root": 34,
    "345gs5662d34": 16
  },
  "TopPasswords": {
    "Password.1234": 2,
    "123123s": 2,
    "utopia": 2,
    "345gs5662d34": 16,
    "3245gs5662d34": 14,
    "321EWQdsa": 2,
    "pokemon123": 2,
    "Web2017": 2,
    "123..com": 2,
    "cns": 2,
    "aa11223344": 2,
    "Ba123456": 2
  }
}