{
  "LastUpdated": "2026-07-12T11:10:24.9180541Z",
  "TotalEvents": 388,
  "TotalScanAttempts": 54,
  "UniqueScanIps": 3,
  "TotalShells": 69,
  "EventCounts": {
    "session_end": 29,
    "session_start": 29,
    "auth_attempt": 27,
    "harvested_credential": 27,
    "shell_session_start": 69,
    "command": 69,
    "command_result": 69,
    "shell_session_end": 69
  },
  "ScansByIp": {
    "92.118.39.71": 46,
    "176.53.159.196": 6,
    "2.57.121.112": 2
  },
  "TopUsernames": {
    "root": 26,
    "admin": 22,
    "support": 4,
    "krystina": 2
  },
  "TopPasswords": {
    "root5678": 2,
    "root6666": 2,
    "root9999": 2,
    "root@123": 2,
    "rootaccess": 2,
    "rootadmin": 2,
    "rootme": 2,
    "rootpass": 2,
    "rootpw": 2,
    "admin": 4,
    "rootroot": 2,
    "toor": 2,
    "welcome": 2,
    "1234": 2,
    "12345": 2,
    "123456": 2,
    "123456789": 4,
    "Admin@123": 2,
    "P@ssw0rd": 2,
    "support": 2,
    "admin#123": 2,
    "admin1": 2,
    "krystina": 2,
    "admin123": 2,
    "admin2024": 2
  }
}