{
  "LastUpdated": "2026-07-16T09:43:58.341257Z",
  "TotalEvents": 129,
  "TotalScanAttempts": 56,
  "UniqueScanIps": 7,
  "TotalShells": 5,
  "EventCounts": {
    "session_start": 29,
    "auth_attempt": 28,
    "harvested_credential": 28,
    "session_end": 24,
    "shell_session_start": 5,
    "command": 5,
    "command_result": 5,
    "shell_session_end": 5
  },
  "ScansByIp": {
    "76.79.213.70": 22,
    "41.93.82.201": 14,
    "2.57.121.112": 6,
    "203.83.234.180": 2,
    "2.57.121.25": 6,
    "149.78.8.0": 4,
    "115.190.64.245": 2
  },
  "TopUsernames": {
    "root": 12,
    "student": 2,
    "admin": 8,
    "cal": 6,
    "sql": 2,
    "esadmin": 4,
    "345gs5662d34": 10,
    "teste": 2,
    "xiaoxiao": 4,
    "saas": 4,
    "ocs": 2
  },
  "TopPasswords": {
    "dragon": 2,
    "student01": 2,
    "1q2w#E$R": 2,
    "cal": 2,
    "cal1": 2,
    "cal123": 2,
    "sql": 2,
    "160384": 2,
    "160290": 2,
    "16021977": 2,
    "@Admin2025": 2,
    "esadmin": 2,
    "345gs5662d34": 10,
    "3245gs5662d34": 8,
    "abc123": 2,
    "Aliyun123": 2,
    "xiaoxiao123": 2,
    "P@ssword123!": 2,
    "saas123": 2,
    "logout": 2,
    "ocs123": 2
  }
}