{
  "LastUpdated": "2026-07-12T10:55:55.9231659Z",
  "TotalEvents": 255,
  "TotalScanAttempts": 34,
  "UniqueScanIps": 2,
  "TotalShells": 46,
  "EventCounts": {
    "session_end": 18,
    "session_start": 19,
    "auth_attempt": 17,
    "harvested_credential": 17,
    "shell_session_start": 46,
    "command": 46,
    "command_result": 46,
    "shell_session_end": 46
  },
  "ScansByIp": {
    "92.118.39.71": 32,
    "176.53.159.196": 2
  },
  "TopUsernames": {
    "root": 26,
    "admin": 8
  },
  "TopPasswords": {
    "root5678": 2,
    "root6666": 2,
    "root9999": 2,
    "root@123": 2,
    "rootaccess": 2,
    "rootadmin": 2,
    "rootme": 2,
    "rootpass": 2,
    "rootpw": 2,
    "admin": 2,
    "rootroot": 2,
    "toor": 2,
    "welcome": 2,
    "1234": 2,
    "12345": 2,
    "123456": 2,
    "123456789": 2
  }
}