{
  "LastUpdated": "2026-07-16T09:56:32.9243047Z",
  "TotalEvents": 15,
  "TotalScanAttempts": 4,
  "UniqueScanIps": 1,
  "TotalShells": 2,
  "EventCounts": {
    "session_start": 3,
    "auth_attempt": 2,
    "harvested_credential": 2,
    "shell_session_start": 2,
    "command": 2,
    "command_result": 2,
    "shell_session_end": 2
  },
  "ScansByIp": {
    "41.93.82.201": 4
  },
  "TopUsernames": {
    "root": 2,
    "345gs5662d34": 2
  },
  "TopPasswords": {
    "!QAZxsw23edc": 2,
    "345gs5662d34": 2
  }
}