{
  "LastUpdated": "2026-07-18T10:58:24.4654935Z",
  "TotalEvents": 716,
  "TotalScanAttempts": 88,
  "UniqueScanIps": 6,
  "TotalShells": 126,
  "EventCounts": {
    "shell_session_start": 126,
    "session_start": 73,
    "command": 127,
    "command_result": 125,
    "shell_session_end": 126,
    "auth_attempt": 44,
    "harvested_credential": 44,
    "session_end": 51
  },
  "ScansByIp": {
    "59.36.78.66": 14,
    "89.163.204.62": 8,
    "4.230.10.211": 18,
    "182.93.7.194": 18,
    "2.57.121.25": 2,
    "200.196.50.91": 28
  },
  "TopUsernames": {
    "apollo": 2,
    "admin": 14,
    "lighthouse": 2,
    "345gs5662d34": 20,
    "nabi": 2,
    "root": 34,
    "dma": 2,
    "hex": 2,
    "frontend": 2,
    "git": 4,
    "xie": 4
  },
  "TopPasswords": {
    "3245gs5662d34": 20,
    "admin12345": 8,
    "123456": 2,
    "345gs5662d34": 20,
    "nabi123": 2,
    "2009": 2,
    "07121982": 2,
    "qwe123asd123": 2,
    "P@ssw0rd123$": 2,
    "aA123456!@#": 2,
    "Passw0rd1": 2,
    "dma123": 2,
    "hex": 2,
    "Root@admin": 2,
    "ben": 2,
    "1": 2,
    "Mm12345": 2,
    "Ff12345678": 2,
    "asd": 2,
    "Passw0rd.123": 2,
    "xie123": 2,
    "123qaz!@#": 2,
    "Ft112233": 2
  }
}