{
  "LastUpdated": "2026-07-10T11:35:17.0950587Z",
  "TotalEvents": 177,
  "TotalScanAttempts": 54,
  "UniqueScanIps": 3,
  "TotalShells": 17,
  "EventCounts": {
    "command_result": 18,
    "shell_session_start": 17,
    "session_start": 33,
    "shell_session_end": 18,
    "command": 17,
    "auth_attempt": 27,
    "harvested_credential": 27,
    "session_end": 20
  },
  "ScansByIp": {
    "24.122.136.94": 18,
    "61.155.106.101": 22,
    "122.35.192.33": 14
  },
  "TopUsernames": {
    "345gs5662d34": 22,
    "root": 12,
    "ubuntu": 2,
    "manjaro": 2,
    "hung": 4,
    "max": 2,
    "cent": 4,
    "lee": 4,
    "mason": 2
  },
  "TopPasswords": {
    "345gs5662d34": 22,
    "3245gs5662d34": 14,
    "P@ssw0rd123456789": 2,
    "manjaro": 2,
    "hung123": 2,
    "qwe321": 2,
    "max": 2,
    "cent": 2,
    "password1": 2,
    "1234": 2,
    "aaAA123123": 2
  }
}