{
  "LastUpdated": "2026-07-20T17:00:00.2423089Z",
  "TotalEvents": 131,
  "TotalScanAttempts": 20,
  "UniqueScanIps": 5,
  "TotalShells": 12,
  "EventCounts": {
    "session_end": 26,
    "shell_session_start": 12,
    "session_start": 37,
    "command": 12,
    "auth_attempt": 10,
    "harvested_credential": 10,
    "command_result": 12,
    "shell_session_end": 12
  },
  "ScansByIp": {
    "14.225.218.99": 10,
    "152.32.172.177": 4,
    "101.32.145.199": 2,
    "217.155.75.149": 2,
    "89.163.204.62": 2
  },
  "TopUsernames": {
    "smart": 2,
    "345gs5662d34": 2,
    "admin1": 2,
    "runner": 4,
    "rahul": 2,
    "admin": 4,
    "root": 4
  },
  "TopPasswords": {
    "3245gs5662d34": 8,
    "345gs5662d34": 2,
    "q1w2e3r4": 2,
    "password": 2,
    "1q2w3e4r5T": 2,
    "$RFVcde3": 2,
    "admin12345": 2
  }
}