{
  "LastUpdated": "2026-07-13T05:04:31.1486871Z",
  "TotalEvents": 148,
  "TotalScanAttempts": 54,
  "UniqueScanIps": 3,
  "TotalShells": 11,
  "EventCounts": {
    "session_start": 29,
    "auth_attempt": 27,
    "harvested_credential": 27,
    "session_end": 21,
    "shell_session_start": 11,
    "command": 11,
    "command_result": 11,
    "shell_session_end": 11
  },
  "ScansByIp": {
    "185.214.101.139": 28,
    "52.176.211.73": 24,
    "2.57.121.25": 2
  },
  "TopUsernames": {
    "345gs5662d34": 16,
    "omid": 2,
    "alvaro": 4,
    "colin": 4,
    "devops": 4,
    "root": 8,
    "oracle": 4,
    "admin": 2,
    "postgres": 4,
    "vpn": 4,
    "mcserver": 2
  },
  "TopPasswords": {
    "345gs5662d34": 16,
    "3245gs5662d34": 18,
    "alvaro": 2,
    "password": 2,
    "devops": 2,
    "Qwer123": 2,
    "adminadmin": 2,
    "748159263": 2,
    "Pa$$w0rd": 2,
    "vpn2025": 2,
    "Tt123456": 2,
    "mc": 2
  }
}