{
  "LastUpdated": "2026-07-12T14:53:58.574795Z",
  "TotalEvents": 239,
  "TotalScanAttempts": 42,
  "UniqueScanIps": 4,
  "TotalShells": 32,
  "EventCounts": {
    "shell_session_start": 32,
    "session_start": 40,
    "command": 32,
    "command_result": 32,
    "shell_session_end": 32,
    "session_end": 29,
    "auth_attempt": 21,
    "harvested_credential": 21
  },
  "ScansByIp": {
    "101.47.156.21": 16,
    "195.178.110.227": 8,
    "182.93.7.194": 14,
    "101.245.108.90": 4
  },
  "TopUsernames": {
    "cvs": 2,
    "root": 20,
    "345gs5662d34": 8,
    "medical": 4,
    "patrick": 2,
    "vnc": 2,
    "deployer": 2,
    "jayesh": 2
  },
  "TopPasswords": {
    "3245gs5662d34": 10,
    "123456": 4,
    "Password1#": 2,
    "345gs5662d34": 8,
    "medical": 2,
    "1234567": 2,
    "password": 2,
    "qwerty12": 2,
    "123456789": 2,
    "Server@123": 2,
    "1234abcd": 2,
    "12345678": 2,
    "jayesh123": 2
  }
}